seame_piracer/__init__.py
seame_piracer/cameras.py
seame_piracer/gamepads.py
seame_piracer/piracer_middleware.py
seame_piracer/vehicles.py
seame_piracer-0.1.2.dist-info/LICENSE
seame_piracer-0.1.2.dist-info/METADATA
seame_piracer-0.1.2.dist-info/WHEEL
seame_piracer-0.1.2.dist-info/top_level.txt
seame_piracer-0.1.2.dist-info/RECORD
