Metadata-Version: 2.1
Name: seame-piracer
Version: 0.1.2
Summary: PiRacer Abstract Layer for SEA:ME DES proejct
Home-page: https://github.com/junho2000/custom_piracer_py
Author: Junho Kim
Author-email: jhk00@kookmin.ac.kr
License: GPL 3.0
Keywords: piracer embedded abstraction
License-File: LICENSE
Requires-Dist: wheel
Requires-Dist: RPi.GPIO
Requires-Dist: adafruit-circuitpython-pca9685
Requires-Dist: adafruit-circuitpython-ina219
Requires-Dist: adafruit-circuitpython-ssd1306
Requires-Dist: opencv-python
